asynchronous_fifo/mem.v
module mem #(parameter width = 3, depth = 8, data_width = 8)(
    input                        wclk, w_en, rclk, r_en,
    input      [width:0]         b_wptr, b_rptr,
    input      [data_width-1:0]  data_in,
    input                        full, empty,
    output reg [data_width-1:0]  data_out
);

    reg [data_width-1:0] fifo [0:depth-1];

    always @(posedge wclk) begin
        if (w_en & !full) begin
            fifo[b_wptr[width-1:0]] <= data_in;
        end
    end

    always @(posedge rclk) begin
        if (r_en & !empty) begin
            data_out <= fifo[b_rptr[width-1:0]];
        end
    end
endmodule

asynchronous_fifo/rptr_handler.v
module rptr_handler #(parameter width = 3)
(
    input                  rclk,
    input                  rrst_n,
    input                  r_ena,
    input      [width:0]   wptr_sync,   // synced Gray write pointer
    output reg [width:0]   g_rrpt,
    output reg [width:0]   b_rrpt,
    output reg             empty
);

    wire [width:0] b_rrpt_next;
    wire [width:0] g_rrpt_next;
    wire           rempty;

    assign b_rrpt_next = b_rrpt + (r_ena & !empty);        // gated by !empty
    assign g_rrpt_next = (b_rrpt_next >> 1) ^ b_rrpt_next; // binary -> gray

    // EMPTY: next gray read ptr == synced write ptr (exact match)
    assign rempty = (g_rrpt_next == wptr_sync);

    // pointer registers
    always @(posedge rclk or negedge rrst_n) begin
        if (!rrst_n) begin
            b_rrpt <= 0;
            g_rrpt <= 0;
        end else begin
            b_rrpt <= b_rrpt_next;
            g_rrpt <= g_rrpt_next;
        end
    end

    // empty flag register
    always @(posedge rclk or negedge rrst_n) begin
        if (!rrst_n) empty <= 1'b1;   // FIFO starts EMPTY
        else         empty <= rempty;
    end
endmodule

asynchronous_fifo/wptr_handler.v
module wptr_handler #(parameter width = 3)
(
    input                  wclk,
    input                  wrst_n,
    input                  wr_ena,
    input      [width:0]   rptr_sync,   // synced Gray read pointer
    output reg [width:0]   g_wrpt,
    output reg [width:0]   b_wrpt,
    output reg             full
);

    wire [width:0] b_wrpt_next;
    wire [width:0] g_wrpt_next;
    wire           wfull;

    assign b_wrpt_next = b_wrpt + (wr_ena & !full);        // gated by !full
    assign g_wrpt_next = (b_wrpt_next >> 1) ^ b_wrpt_next; // binary -> gray

    // FULL: next gray write ptr == synced read ptr with top 2 bits inverted
    // (classic Gray-code identity - only valid when both sides are Gray)
    assign wfull = (g_wrpt_next == {~rptr_sync[width:width-1],
                                       rptr_sync[width-2:0]});

    // pointer registers
    always @(posedge wclk or negedge wrst_n) begin
        if (!wrst_n) begin
            b_wrpt <= 0;
            g_wrpt <= 0;
        end else begin
            b_wrpt <= b_wrpt_next;
            g_wrpt <= g_wrpt_next;
        end
    end

    // full flag register
    always @(posedge wclk or negedge wrst_n) begin
        if (!wrst_n) full <= 1'b0;   // FIFO starts NOT full
        else         full <= wfull;
    end
endmodule

asynchronous_fifo/synchronizer.v
module synchronizer #(parameter width = 8)(
    input                  clk,
    input                  rst_n,
    input      [width:0]   din,
    output reg [width:0]   dout
);

    reg [width:0] q;

    always @(posedge clk or negedge rst_n) begin
        if (!rst_n) begin
            q    <= 0;
            dout <= 0;
        end else begin
            q    <= din;   // flop 1 - may go metastable
            dout <= q;     // flop 2 - resolved, safe to use
        end
    end
endmodule

asynchronous_fifo/async_fifo_top.v
`include "synchronizer.v"
`include "wptr_handler.v"
`include "rptr_handler.v"
`include "mem.v"
module asynchronous_fifo #(parameter depth = 8, data_width = 8) (
    input                        wclk, wrst_n,
    input                        rclk, rrst_n,
    input                        w_en, r_en,
    input      [data_width-1:0]  data_in,
    output     [data_width-1:0]  data_out,
    output                       full, empty
);

    localparam width = $clog2(depth);   // ADDR_WIDTH

    wire [width:0] g_wptr, b_wptr;
    wire [width:0] g_rptr, b_rptr;
    wire [width:0] g_wptr_sync, g_rptr_sync;

    // write pointer (gray) synced into read clock domain
    synchronizer #(width) sync_wptr (
        .clk   (rclk),
        .rst_n (rrst_n),
        .din   (g_wptr),
        .dout  (g_wptr_sync)
    );

    // read pointer (gray) synced into write clock domain
    synchronizer #(width) sync_rptr (
        .clk   (wclk),
        .rst_n (wrst_n),
        .din   (g_rptr),
        .dout  (g_rptr_sync)
    );

    wptr_handler #(width) wptr_h (
        .wclk      (wclk),
        .wrst_n    (wrst_n),
        .wr_ena    (w_en),
        .rptr_sync (g_rptr_sync),
        .g_wrpt    (g_wptr),
        .b_wrpt    (b_wptr),
        .full      (full)
    );

    rptr_handler #(width) rptr_h (
        .rclk      (rclk),
        .rrst_n    (rrst_n),
        .r_ena     (r_en),
        .wptr_sync (g_wptr_sync),
        .g_rrpt    (g_rptr),
        .b_rrpt    (b_rptr),
        .empty     (empty)
    );

    mem #(width, depth, data_width) fifo_mem (
        .wclk     (wclk),
        .w_en     (w_en),
        .rclk     (rclk),
        .r_en     (r_en),
        .b_wptr   (b_wptr),
        .b_rptr   (b_rptr),
        .data_in  (data_in),
        .full     (full),
        .empty    (empty),
        .data_out (data_out)
    );

endmodule

asynchronous_fifo/async_fifo_tb.v
`timescale 1ns/1ps

module async_fifo_tb;

    localparam DEPTH      = 8;
    localparam DATA_WIDTH = 8;

    reg                     wclk, wrst_n;
    reg                     rclk, rrst_n;
    reg                     w_en, r_en;
    reg  [DATA_WIDTH-1:0]   data_in;
    wire [DATA_WIDTH-1:0]   data_out;
    wire                    full, empty;

    integer wr_count;
    integer rd_count;
    integer wi;   // write-process loop variable (separate from read's, since
    integer ri;   // both initial blocks run concurrently - sharing one variable
                  // between them was a real bug: each process stomped on the
                  // other's loop counter mid-run)
    reg [DATA_WIDTH-1:0] expected;      // used by the comparison check
    reg [DATA_WIDTH-1:0] expected_disp; // purely cosmetic: mirrors `expected`
                                         // but updates on the SAME rclk edge
                                         // as data_out, so the two traces line
                                         // up visually in the waveform viewer.
                                         // Has no effect on the pass/fail check.

    asynchronous_fifo #(.depth(DEPTH), .data_width(DATA_WIDTH)) DUT (
        .wclk     (wclk),
        .wrst_n   (wrst_n),
        .rclk     (rclk),
        .rrst_n   (rrst_n),
        .w_en     (w_en),
        .r_en     (r_en),
        .data_in  (data_in),
        .data_out (data_out),
        .full     (full),
        .empty    (empty)
    );

    //-----------------------------------------------------------------
    // Independent clocks - different periods, no common phase.
    //-----------------------------------------------------------------
    initial wclk = 0;
    always #5  wclk = ~wclk;   // 10ns period -> 100MHz

    initial rclk = 0;
    always #7  rclk = ~rclk;   // 14ns period -> ~71MHz

    //-----------------------------------------------------------------
    // Reset
    //-----------------------------------------------------------------
    initial begin
        wrst_n   = 0;
        rrst_n   = 0;
        w_en     = 0;
        r_en     = 0;
        data_in  = 0;
        wr_count = 0;
        rd_count = 0;
        expected = 0;

        #20;
        wrst_n = 1;
        rrst_n = 1;
    end

    //-----------------------------------------------------------------
    // Write process: push DEPTH+2 words (more than depth, to prove
    // `full` actually blocks writes and nothing overflows/corrupts).
    //-----------------------------------------------------------------
    initial begin
        wait (wrst_n == 1);
        @(posedge wclk);

        for (wi = 0; wi < DEPTH + 2; wi = wi + 1) begin
            @(posedge wclk);
            while (full) @(posedge wclk);      // stall while full
            w_en    <= 1;
            data_in <= wi;
            @(posedge wclk);
            w_en    <= 0;
            wr_count = wr_count + 1;
        end

        $display("[%0t] WRITE: pushed %0d words", $time, wr_count);
    end

    //-----------------------------------------------------------------
    // Read process: starts a bit later, drains everything written,
    // verifying FIFO order (first word in must be first word out).
    //-----------------------------------------------------------------
    initial begin
        wait (rrst_n == 1);
        #50;   // let a few writes accumulate first

        for (ri = 0; ri < DEPTH + 2; ri = ri + 1) begin
            @(posedge rclk);
            while (empty) @(posedge rclk);     // stall while empty
            r_en <= 1;
            @(posedge rclk);                   // edge where data_out updates
            r_en <= 0;
            #1;                                 // let data_out settle post-edge
            if (data_out !== expected)
                $display("[%0t] MISMATCH: expected %0d, got %0d",
                          $time, expected, data_out);
            else
                $display("[%0t] READ OK: got %0d", $time, data_out);
            rd_count = rd_count + 1;
            expected = expected + 1;
        end
    end

    //-----------------------------------------------------------------
    // Cosmetic-only: expected_disp changes on the exact same rclk edge
    // that data_out changes (i.e. when r_en was high on the prior edge),
    // so the two traces overlay cleanly in a waveform viewer. This plays
    // no role in the actual pass/fail check above.
    //-----------------------------------------------------------------
    initial expected_disp = 0;
    always @(posedge rclk) begin
        if (r_en) expected_disp <= expected_disp + 1;
    end

    //-----------------------------------------------------------------
    // Flag monitors
    //-----------------------------------------------------------------
    always @(posedge full)  $display("[%0t] FULL asserted",   $time);
    always @(negedge full)  $display("[%0t] FULL deasserted",  $time);
    always @(posedge empty) $display("[%0t] EMPTY asserted",   $time);
    always @(negedge empty) $display("[%0t] EMPTY deasserted", $time);

    //-----------------------------------------------------------------
    // Finish
    //-----------------------------------------------------------------
    initial begin
        #2000;
        $display("Simulation done. wr_count=%0d rd_count=%0d", wr_count, rd_count);
        $finish;
    end

    //-----------------------------------------------------------------
    // Waveform dump
    //-----------------------------------------------------------------
    initial begin
        $dumpfile("async_fifo_tb.vcd");
        $dumpvars(0, async_fifo_tb);
    end

endmodule

asynchronous_fifo/async_fifo_tb.vcd
$date
	Sat Aug 22 16:56:48 2026
$end
$version
	Icarus Verilog
$end
$timescale
	1ps
$end
$scope module async_fifo_tb $end
$var wire 8 ! data_out [7:0] $end
$var wire 1 " empty $end
$var wire 1 # full $end
$var reg 8 $ data_in [7:0] $end
$var reg 8 % expected [7:0] $end
$var reg 8 & expected_disp [7:0] $end
$var reg 1 ' r_en $end
$var reg 1 ( rclk $end
$var integer 32 ) rd_count [31:0] $end
$var integer 32 * ri [31:0] $end
$var reg 1 + rrst_n $end
$var reg 1 , w_en $end
$var reg 1 - wclk $end
$var integer 32 . wi [31:0] $end
$var integer 32 / wr_count [31:0] $end
$var reg 1 0 wrst_n $end
$scope module DUT $end
$var wire 4 1 b_rptr [3:0] $end
$var wire 4 2 b_wptr [3:0] $end
$var wire 8 3 data_in [7:0] $end
$var wire 8 4 data_out [7:0] $end
$var wire 1 " empty $end
$var wire 1 # full $end
$var wire 4 5 g_rptr [3:0] $end
$var wire 4 6 g_rptr_sync [3:0] $end
$var wire 4 7 g_wptr [3:0] $end
$var wire 4 8 g_wptr_sync [3:0] $end
$var wire 1 9 r_en $end
$var wire 1 : rclk $end
$var wire 1 ; rrst_n $end
$var wire 1 < w_en $end
$var wire 1 = wclk $end
$var wire 1 > wrst_n $end
$scope module sync_wptr $end
$var wire 1 : clk $end
$var wire 4 ? din [3:0] $end
$var wire 1 ; rst_n $end
$var reg 4 @ dout [3:0] $end
$var reg 4 A q [3:0] $end
$upscope $end
$scope module sync_rptr $end
$var wire 1 = clk $end
$var wire 4 B din [3:0] $end
$var wire 1 > rst_n $end
$var reg 4 C dout [3:0] $end
$var reg 4 D q [3:0] $end
$upscope $end
$scope module wptr_h $end
$var wire 4 E b_wrpt_next [3:0] $end
$var wire 4 F g_wrpt_next [3:0] $end
$var wire 4 G rptr_sync [3:0] $end
$var wire 1 = wclk $end
$var wire 1 H wfull $end
$var wire 1 < wr_ena $end
$var wire 1 > wrst_n $end
$var reg 4 I b_wrpt [3:0] $end
$var reg 1 J full $end
$var reg 4 K g_wrpt [3:0] $end
$upscope $end
$scope module rptr_h $end
$var wire 4 L b_rrpt_next [3:0] $end
$var wire 4 M g_rrpt_next [3:0] $end
$var wire 1 9 r_ena $end
$var wire 1 : rclk $end
$var wire 1 N rempty $end
$var wire 1 ; rrst_n $end
$var wire 4 O wptr_sync [3:0] $end
$var reg 4 P b_rrpt [3:0] $end
$var reg 1 Q empty $end
$var reg 4 R g_rrpt [3:0] $end
$upscope $end
$scope module fifo_mem $end
$var wire 4 S b_rptr [3:0] $end
$var wire 4 T b_wptr [3:0] $end
$var wire 8 U data_in [7:0] $end
$var wire 1 " empty $end
$var wire 1 # full $end
$var wire 1 9 r_en $end
$var wire 1 : rclk $end
$var wire 1 < w_en $end
$var wire 1 = wclk $end
$var reg 8 V data_out [7:0] $end
$upscope $end
$upscope $end
$upscope $end
$enddefinitions $end
#0
$dumpvars
bx V
b0 U
b0 T
b0 S
b0 R
1Q
b0 P
b0 O
1N
b0 M
b0 L
b0 K
0J
b0 I
0H
b0 G
b0 F
b0 E
b0 D
b0 C
b0 B
b0 A
b0 @
b0 ?
0>
0=
0<
0;
0:
09
b0 8
b0 7
b0 6
b0 5
bx 4
b0 3
b0 2
b0 1
00
b0 /
bx .
0-
0,
0+
bx *
b0 )
0(
0'
b0 &
b0 %
b0 $
0#
1"
bx !
$end
#5000
1-
1=
#7000
1(
1:
#10000
0-
0=
#14000
0(
0:
#15000
1-
1=
#20000
0-
0=
1+
1;
10
1>
#21000
1(
1:
#25000
b0 .
1-
1=
#28000
0(
0:
#30000
0-
0=
#35000
b1 F
b1 E
1,
1<
1-
1=
1(
1:
#40000
0-
0=
#42000
0(
0:
#45000
b1 F
0,
0<
b1 K
b1 7
b1 ?
b1 I
b1 E
b1 2
b1 T
b1 .
b1 /
1-
1=
#49000
b1 A
1(
1:
#50000
0-
0=
#55000
b11 F
b10 E
b1 $
b1 3
b1 U
1,
1<
1-
1=
#56000
0(
0:
#60000
0-
0=
#63000
b1 @
0N
b1 8
b1 O
1(
1:
#65000
b11 F
0,
0<
b11 K
b11 7
b11 ?
b10 I
b10 E
b10 2
b10 T
b10 .
b10 /
1-
1=
#70000
0-
0=
0(
0:
b0 *
#75000
b10 F
b11 E
b10 $
b10 3
b10 U
1,
1<
1-
1=
#77000
b11 A
0Q
0"
1(
1:
#80000
0-
0=
#84000
0(
0:
#85000
b10 F
0,
0<
b10 K
b10 7
b10 ?
b11 I
b11 E
b11 2
b11 T
b11 .
b11 /
1-
1=
#90000
0-
0=
#91000
b1 M
b1 L
1'
19
b11 @
b11 8
b11 O
b10 A
1(
1:
#95000
b110 F
b100 E
b11 $
b11 3
b11 U
1,
1<
1-
1=
#98000
0(
0:
#100000
0-
0=
#105000
b110 F
b1 M
0N
0,
0<
b110 K
b110 7
b110 ?
b100 I
b100 E
b100 2
b100 T
b1 &
b0 V
b0 !
b0 4
0'
09
b10 @
b10 8
b10 O
b1 R
b1 5
b1 B
b1 P
b1 L
b1 1
b1 S
b100 .
b100 /
1-
1=
1(
1:
#106000
b1 *
b1 %
b1 )
#110000
0-
0=
#112000
0(
0:
#115000
b111 F
b101 E
b100 $
b100 3
b100 U
1,
1<
b1 D
1-
1=
#119000
b11 M
0N
b10 L
1'
19
b110 A
1(
1:
#120000
0-
0=
#125000
b111 F
0,
0<
b111 K
b111 7
b111 ?
b101 I
b101 E
b101 2
b101 T
b1 C
b1 6
b1 G
b101 .
b101 /
1-
1=
#126000
0(
0:
#130000
0-
0=
#133000
b11 M
0'
09
b10 &
b1 V
b1 !
b1 4
b110 @
b110 8
b110 O
b111 A
b11 R
b11 5
b11 B
b10 P
b10 L
b10 1
b10 S
1(
1:
#134000
b10 *
b10 %
b10 )
#135000
b101 F
b110 E
b101 $
b101 3
b101 U
1,
1<
b11 D
1-
1=
#140000
0-
0=
0(
0:
#145000
b101 F
0,
0<
b101 K
b101 7
b101 ?
b110 I
b110 E
b110 2
b110 T
b11 C
b11 6
b11 G
b110 .
b110 /
1-
1=
#147000
b10 M
b11 L
1'
19
b111 @
b111 8
b111 O
b101 A
1(
1:
#150000
0-
0=
#154000
0(
0:
#155000
b100 F
b111 E
b110 $
b110 3
b110 U
1,
1<
1-
1=
#160000
0-
0=
#161000
b10 M
0N
0'
09
b11 &
b10 V
b10 !
b10 4
b101 @
b101 8
b101 O
b10 R
b10 5
b10 B
b11 P
b11 L
b11 1
b11 S
1(
1:
#162000
b11 *
b11 %
b11 )
#165000
b100 F
0,
0<
b100 K
b100 7
b100 ?
b111 I
b111 E
b111 2
b111 T
b10 D
b111 .
b111 /
1-
1=
#168000
0(
0:
#170000
0-
0=
#175000
b1100 F
b110 M
0N
b1000 E
b100 L
b111 $
b111 3
b111 U
1,
1<
b10 C
b10 6
b10 G
1'
19
b100 A
1-
1=
1(
1:
#180000
0-
0=
#182000
0(
0:
#185000
b1100 F
0,
0<
b1100 K
b1100 7
b1100 ?
b1000 I
b1000 E
b1000 2
b1000 T
b1000 .
b1000 /
1-
1=
#189000
b110 M
0'
09
b100 &
b11 V
b11 !
b11 4
b100 @
b100 8
b100 O
b1100 A
b110 R
b110 5
b110 B
b100 P
b100 L
b100 1
b100 S
1(
1:
#190000
b100 *
b100 %
b100 )
0-
0=
#195000
b1101 F
b1001 E
b1000 $
b1000 3
b1000 U
1,
1<
b110 D
1-
1=
#196000
0(
0:
#200000
0-
0=
#203000
b111 M
b101 L
1'
19
b1100 @
b1100 8
b1100 O
1(
1:
#205000
b1101 F
0H
0,
0<
b1101 K
b1101 7
b1101 ?
b1001 I
b1001 E
b1001 2
b1001 T
b110 C
b110 6
b110 G
b1001 .
b1001 /
1-
1=
#210000
0-
0=
0(
0:
#215000
b1111 F
b1010 E
b1001 $
b1001 3
b1001 U
1,
1<
1-
1=
#217000
b111 M
0'
09
b101 &
b100 V
b100 !
b100 4
b1101 A
b111 R
b111 5
b111 B
b101 P
b101 L
b101 1
b101 S
1(
1:
#218000
b101 *
b101 %
b101 )
#220000
0-
0=
#224000
0(
0:
#225000
b1111 F
0,
0<
b1111 K
b1111 7
b1111 ?
b1010 I
b1010 E
b1010 2
b1010 T
b111 D
b1010 .
b1010 /
1-
1=
#230000
0-
0=
#231000
b101 M
b110 L
1'
19
b1101 @
b1101 8
b1101 O
b1111 A
1(
1:
#235000
b111 C
b111 6
b111 G
1-
1=
#238000
0(
0:
#240000
0-
0=
#245000
b101 M
0'
09
b110 &
b101 V
b101 !
b101 4
b1111 @
b1111 8
b1111 O
b101 R
b101 5
b101 B
b110 P
b110 L
b110 1
b110 S
1-
1=
1(
1:
#246000
b110 *
b110 %
b110 )
#250000
0-
0=
#252000
0(
0:
#255000
b101 D
1-
1=
#259000
b100 M
b111 L
1'
19
1(
1:
#260000
0-
0=
#265000
b101 C
b101 6
b101 G
1-
1=
#266000
0(
0:
#270000
0-
0=
#273000
b100 M
0'
09
b111 &
b110 V
b110 !
b110 4
b100 R
b100 5
b100 B
b111 P
b111 L
b111 1
b111 S
1(
1:
#274000
b111 *
b111 %
b111 )
#275000
b100 D
1-
1=
#280000
0-
0=
0(
0:
#285000
b100 C
b100 6
b100 G
1-
1=
#287000
b1100 M
b1000 L
1'
19
1(
1:
#290000
0-
0=
#294000
0(
0:
#295000
1-
1=
#300000
0-
0=
#301000
b1100 M
0'
09
b1000 &
b111 V
b111 !
b111 4
b1100 R
b1100 5
b1100 B
b1000 P
b1000 L
b1000 1
b1000 S
1(
1:
#302000
b1000 *
b1000 %
b1000 )
#305000
b1100 D
1-
1=
#308000
0(
0:
#310000
0-
0=
#315000
b1101 M
b1001 L
b1100 C
b1100 6
b1100 G
1'
19
1-
1=
1(
1:
#320000
0-
0=
#322000
0(
0:
#325000
1-
1=
#329000
b1101 M
0'
09
b1001 &
b1000 V
b1000 !
b1000 4
b1101 R
b1101 5
b1101 B
b1001 P
b1001 L
b1001 1
b1001 S
1(
1:
#330000
b1001 *
b1001 %
b1001 )
0-
0=
#335000
b1101 D
1-
1=
#336000
0(
0:
#340000
0-
0=
#343000
1N
b1111 M
b1010 L
1'
19
1(
1:
#345000
b1101 C
b1101 6
b1101 G
1-
1=
#350000
0-
0=
0(
0:
#355000
1-
1=
#357000
0'
09
b1010 &
b1001 V
b1001 !
b1001 4
b1111 R
b1111 5
b1111 B
b1010 P
b1010 L
b1010 1
b1010 S
1Q
1"
1(
1:
#358000
b1010 *
b1010 %
b1010 )
#360000
0-
0=
#364000
0(
0:
#365000
b1111 D
1-
1=
#370000
0-
0=
#371000
1(
1:
#375000
b1111 C
b1111 6
b1111 G
1-
1=
