synchronous_fifo/sync_fifo.v
module sync_fifo #(parameter DEPTH = 8, DATA_WIDTH = 8)(
    input clk,
    input rst_n,
    input wr_en,
    input rd_en,
    input [DATA_WIDTH-1:0] data_in,
    output reg [DATA_WIDTH-1:0] data_out,
    output full,
    output empty
);

localparam PTR_W = $clog2(DEPTH);
integer i;
reg [DATA_WIDTH-1:0] mem [0:DEPTH-1];
reg [PTR_W-1:0] w_ptr, r_ptr;  
reg w_phase, r_phase;            

assign full  = (w_ptr == r_ptr) && (w_phase != r_phase);
assign empty = (w_ptr == r_ptr) && (w_phase == r_phase);

always @(posedge clk or negedge rst_n) begin
    if (!rst_n) begin
        w_ptr   <= 0;
        r_ptr   <= 0;
        w_phase <= 0;
        r_phase <= 0;
        data_out <= 0;
        for(i = 0;i < DEPTH;i = i + 1)begin
            mem[i] <= 0;
        end
    end
    else begin
        if (wr_en && !full) begin
            mem[w_ptr] <= data_in;
            if (w_ptr == DEPTH-1) begin
                w_ptr   <= 0;
                w_phase <= ~w_phase;
            end else begin
                w_ptr <= w_ptr + 1;
            end
        end
        if (rd_en && !empty) begin
            data_out <= mem[r_ptr];
            if (r_ptr == DEPTH-1) begin
                r_ptr   <= 0;
                r_phase <= ~r_phase;
            end else begin
                r_ptr <= r_ptr + 1;
            end
        end
    end
end

endmodule

synchronous_fifo/tb_fifo.v
`timescale 1ns / 1ps

module tb_fifo;

    reg clk, rst_n, wr_en, rd_en;
    reg [7:0] data_in;
    wire [7:0] data_out;
    wire full, empty;

    sync_fifo uut (
        .clk      (clk),
        .rst_n    (rst_n),
        .wr_en    (wr_en),
        .rd_en    (rd_en),
        .data_in  (data_in),
        .data_out (data_out),
        .full     (full),
        .empty    (empty)
    );

    // Clock
    initial begin
        clk = 0;
        forever #5 clk = ~clk;
    end

    initial begin
        // GTKWave dump
        $dumpfile("sync_fifo.vcd");
        $dumpvars(0, tb_fifo);

        // Reset
        rst_n   = 0;
        wr_en   = 0;
        rd_en   = 0;
        data_in = 0;

        #10 rst_n = 1;

        // Write 4 values
        repeat (4) begin
            @(negedge clk);
            wr_en   = 1;
            data_in = $random;
        end

        @(negedge clk);
        wr_en = 0;

        // Read 4 values
        repeat (4) begin
            @(negedge clk);
            rd_en = 1;
        end

        @(negedge clk);
        rd_en = 0;

        #20 $finish;
    end

endmodule

synchronous_fifo/sync_fifo.vcd
$date
	Sat Aug 22 18:16:51 2026
$end
$version
	Icarus Verilog
$end
$timescale
	1ps
$end
$scope module tb_fifo $end
$var wire 8 ! data_out [7:0] $end
$var wire 1 " empty $end
$var wire 1 # full $end
$var reg 1 $ clk $end
$var reg 8 % data_in [7:0] $end
$var reg 1 & rd_en $end
$var reg 1 ' rst_n $end
$var reg 1 ( wr_en $end
$scope module uut $end
$var wire 1 ) clk $end
$var wire 8 * data_in [7:0] $end
$var wire 1 " empty $end
$var wire 1 # full $end
$var wire 1 + rd_en $end
$var wire 1 , rst_n $end
$var wire 1 - wr_en $end
$var reg 8 . data_out [7:0] $end
$var integer 32 / i [31:0] $end
$var reg 1 0 r_phase $end
$var reg 3 1 r_ptr [2:0] $end
$var reg 1 2 w_phase $end
$var reg 3 3 w_ptr [2:0] $end
$upscope $end
$upscope $end
$enddefinitions $end
#0
$dumpvars
b0 3
02
b0 1
00
b1000 /
b0 .
0-
0,
0+
b0 *
0)
0(
0'
0&
b0 %
0$
0#
1"
b0 !
$end
#5000
b1000 /
1$
1)
#10000
b100100 %
b100100 *
1(
1-
0$
0)
1'
1,
#15000
0"
b1 3
1$
1)
#20000
b10000001 %
b10000001 *
0$
0)
#25000
b10 3
1$
1)
#30000
b1001 %
b1001 *
0$
0)
#35000
b11 3
1$
1)
#40000
b1100011 %
b1100011 *
0$
0)
#45000
b100 3
1$
1)
#50000
0(
0-
0$
0)
#55000
1$
1)
#60000
1&
1+
0$
0)
#65000
b1 1
b100100 .
b100100 !
1$
1)
#70000
0$
0)
#75000
b10 1
b10000001 .
b10000001 !
1$
1)
#80000
0$
0)
#85000
b11 1
b1001 .
b1001 !
1$
1)
#90000
0$
0)
#95000
1"
b100 1
b1100011 .
b1100011 !
1$
1)
#100000
0&
0+
0$
0)
